semsql/__init__.py
semsql/builder/build.Makefile
semsql/builder/builder.py
semsql/builder/cli.py
semsql/builder/exclude-terms.txt
semsql/builder/indexes/all-indexes.sql
semsql/builder/prefixes/obo_prefixes.csv
semsql/builder/prefixes/obo_prefixes.db
semsql/builder/prefixes/obo_prefixes.owl
semsql/builder/prefixes/obo_prefixes.ttl
semsql/builder/prefixes/prefix.sql
semsql/builder/prefixes/prefix_ddl.sql
semsql/builder/prefixes/prefixes.csv
semsql/builder/prefixes/prefixes_curated.csv
semsql/builder/prefixes/prefixes_local.csv
semsql/builder/registry/__init__.py
semsql/builder/registry/ontologies.yaml
semsql/builder/registry/registry_schema.py
semsql/builder/registry/registry_schema.yaml
semsql/builder/sql_schema/obo.sql
semsql/builder/sql_schema/omo.sql
semsql/builder/sql_schema/owl.sql
semsql/builder/sql_schema/rdf.sql
semsql/builder/sql_schema/relation_graph.sql
semsql/builder/sql_schema/semsql.sql
semsql/linkml/__init__.py
semsql/linkml/basics.yaml
semsql/linkml/chebi.yaml
semsql/linkml/nlp.yaml
semsql/linkml/obo.yaml
semsql/linkml/omo.yaml
semsql/linkml/owl.yaml
semsql/linkml/rdf.yaml
semsql/linkml/relation_graph.yaml
semsql/linkml/ro.yaml
semsql/linkml/semsql.yaml
semsql/linkml/similarity.yaml
semsql/linkml/taxon_constraints.yaml
semsql/linkml/term_associations.yaml
semsql/loader.py
semsql/ontlib/README.md
semsql/ontlib/__init__.py
semsql/ontlib/common_queries.py
semsql/ontlib/subgraph.py
semsql/sqla/README.md
semsql/sqla/__init__.py
semsql/sqla/nlp.py
semsql/sqla/obo.py
semsql/sqla/omo.py
semsql/sqla/owl.py
semsql/sqla/rdf.py
semsql/sqla/relation_graph.py
semsql/sqla/semsql.py
semsql/sqlutils/__init__.py
semsql/sqlutils/reportgen.py
semsql/sqlutils/view2table.py
semsql/sqlutils/viewgen.py
semsql/utils/__init__.py
semsql/utils/makefile_utils.py
semsql-0.3.3.dist-info/METADATA
semsql-0.3.3.dist-info/WHEEL
semsql-0.3.3.dist-info/entry_points.txt
semsql-0.3.3.dist-info/RECORD
