Metadata-Version: 2.1
Name: semsql
Version: 0.3.3
Summary: 
Author: cmungall
Author-email: cjm@berkeleybop.org
Requires-Python: >=3.8,<4.0
Classifier: Programming Language :: Python :: 3
Classifier: Programming Language :: Python :: 3.8
Classifier: Programming Language :: Python :: 3.9
Classifier: Programming Language :: Python :: 3.10
Classifier: Programming Language :: Python :: 3.11
Classifier: Programming Language :: Python :: 3.12
Requires-Dist: SQLAlchemy-Utils (>=0.38.2,<0.39.0)
Requires-Dist: click (>=8.1.3,<9.0.0)
Requires-Dist: linkml-runtime (>=1.2.15,<2.0.0)
